{"py/object": "rasa.core.featurizers.tracker_featurizers.MaxHistoryTrackerFeaturizer", "state_featurizer": {"py/object": "rasa.core.featurizers.single_state_featurizer.SingleStateFeaturizer", "_default_feature_states": {"intent": {"affirm": 0, "ask_rebellion_year_start": 1, "back": 2, "bot_challenge": 3, "deny": 4, "goodbye": 5, "greet": 6, "mood_great": 7, "mood_unhappy": 8, "nlu_fallback": 9, "out_of_scope": 10, "rebellion_antagonist": 11, "rebellion_county": 12, "rebellion_demands": 13, "rebellion_economic_motivation": 14, "rebellion_end": 15, "rebellion_place_end": 16, "rebellion_priest": 17, "rebellion_protagonist": 18, "rebellion_religious_motivation": 19, "rebellion_response_to_demands": 20, "rebellion_social_motivation": 21, "rebellion_start": 22, "rebellion_taxes": 23, "rebellion_year_start": 24, "restart": 25, "session_start": 26, "tyler_death": 27, "who_wat_tyler": 28}, "action_name": {"action_listen": 0, "action_restart": 1, "action_session_start": 2, "action_default_fallback": 3, "action_deactivate_loop": 4, "action_revert_fallback_events": 5, "action_default_ask_affirmation": 6, "action_default_ask_rephrase": 7, "action_two_stage_fallback": 8, "action_unlikely_intent": 9, "action_back": 10, "...": 11, "action_extract_slots": 12, "action_ask_rebellion_year_start": 13, "action_evaluate_rebellion_year_start": 14, "utter_actual_score": 15, "utter_cheer_up": 16, "utter_did_that_help": 17, "utter_goodbye": 18, "utter_greet": 19, "utter_happy": 20, "utter_iamabot": 21, "utter_rebellion_antagonist": 22, "utter_rebellion_county": 23, "utter_rebellion_demands": 24, "utter_rebellion_economic_motivation": 25, "utter_rebellion_end": 26, "utter_rebellion_place_end": 27, "utter_rebellion_priest": 28, "utter_rebellion_protagonist": 29, "utter_rebellion_religious_motivation": 30, "utter_rebellion_response_to_demands": 31, "utter_rebellion_social_motivation": 32, "utter_rebellion_start": 33, "utter_rebellion_taxes": 34, "utter_rebellion_year_start": 35}, "entities": {}, "slots": {"score_0": 0, "score_1": 1}, "active_loop": {}}, "action_texts": [], "entity_tag_specs": []}, "max_history": 5, "remove_duplicates": true}